{	"appData" : 	{		"annotations" : [],		"model" : 		{			"quality16k" : "modelfiles/?",			"quality2k" : "modelfiles/88981269-BEA8-0D4D-8E64-1DB7CB0B7F14_2k.glb",			"quality4k" : "modelfiles/?",			"quality512" : "modelfiles/88981269-BEA8-0D4D-8E64-1DB7CB0B7F14_512.glb",			"quality8k" : "modelfiles/?"		},		"modelViewer" : 		{			"cameraField" : "20.720751408334472deg",			"cameraOrbit" : "2.7825536929166175rad 1.5184366775060172rad 1.1173657237540269m",			"cameraTarget" : "-0.00025333841313113226m 0.016294990553660682m 0.0031231592529366026m"		}	},	"basicData" : 	{		"categories" : [ "Haus und Wohnen", "Ökonomische Aspekte" ],		"description" : "",		"key" : "9",		"name" : "Teelichtofen",		"release" : "1",		"tags" : [ "", "Metall", "Ton", "" ]	},	"collectionData" : 	{		"collectionContext" : "",		"collectionDate" : "14.04.2023",		"collectionLocation" : "Regensburg",		"collectionLocationCode" : "93047 ",		"collectionScanner" : "Artec Leo",		"interviewFileName" : "?",		"transcriptFileName" : "230414_VW_Teelichtofen_Transkription.docx"	},	"objectData" : 	{		"alternativeName" : "Schwedenofen",		"datingFrom" : "2021",		"datingTo" : "2022",		"location" : "Lappersdorf",		"locationCode" : "93138",		"origin" : "Lappersdorf",		"originCode" : "93138",		"usageContext" : "Der Teelichtofen besteht aus einem Blumentopf und aus einem Gewindestab aus dem Baumarkt. Als Wärmequelle werden Teelichter genutzt. Darüber hinaus sind Filzgleiter angebracht, die den Tisch, auf dem der kleine Ofen steht, vor etwaigen Schäden bewahren.\r\rDer selbstgebaute Ofen wird in der kalten Jahreszeit täglich im Wohnzimmer verwendet und erhöht die Raumtemperatur bis zu zwei Grad Celsius.\r\rHintergrund der Ofenanfertigung war der Gedanke, Energie für die Heizung zu sparen. Außerdem würden die Kerzen ein angenehmes Licht abgeben."	},	"primaryKey" : "88981269-BEA8-0D4D-8E64-1DB7CB0B7F14"}