{	"appData" : 	{		"annotations" : [],		"model" : 		{			"quality16k" : "modelfiles/?",			"quality2k" : "modelfiles/B412FD2F-4E97-114D-A41A-5B0B9F80A0E0_2k.glb",			"quality4k" : "modelfiles/?",			"quality512" : "modelfiles/B412FD2F-4E97-114D-A41A-5B0B9F80A0E0_512.glb",			"quality8k" : "modelfiles/?"		},		"modelViewer" : 		{			"cameraField" : "24.415351942429382deg",			"cameraOrbit" : "1.732447156067275rad 1.2090655623408038rad 0.993581075080654m",			"cameraTarget" : "0m 0m 0m"		}	},	"basicData" : 	{		"categories" : [ "Spiel und Unterhaltung" ],		"description" : "",		"key" : "57",		"name" : "Holzspielzeug",		"release" : "1",		"tags" : [ "Kindheit und Jugend", "Holz/Haselnuss", "Schnitzen", "Sägen" ]	},	"collectionData" : 	{		"collectionContext" : "",		"collectionDate" : "12.10.2023",		"collectionLocation" : "Neusath (FMO)",		"collectionLocationCode" : "92507",		"collectionScanner" : "botspot Botscan",		"interviewFileName" : "?",		"transcriptFileName" : "231012_ET_Mißbach_Holzspielzeug_Interview_Transkript.docx"	},	"objectData" : 	{		"alternativeName" : "",		"datingFrom" : "2023",		"datingTo" : "2023",		"location" : "Ensdorf",		"locationCode" : "92266",		"origin" : "Ensdorf",		"originCode" : "92266",		"usageContext" : "Ricardo M. baute im Alter von 12 Jahren das Spielzeug aus Holz, welches er im Garten und in seinem \"Kinderschuppen\" gefunden hatte. Das Werken mit Holz bereitet ihm Freude, sodass er  zuvor schon beispielsweise Schwerter geschnitzt hatte. \rBesondere Konzentration war beim Bau des filigranen Bestecks gefordert. \r\rDie selbstgebauten Miniaturmöbel stehen auf der Fensterbank im Zimmer von Ricardos Bruder, der damit bereits ein paar Mal spielte."	},	"primaryKey" : "B412FD2F-4E97-114D-A41A-5B0B9F80A0E0",	"timeStamp" : "28.04.2025 17:44:31"}